xts_cipher/__init__.py
xts_cipher/decryption.py
xts_cipher/encryption.py
xts_cipher-0.2.dist-info/LICENSE
xts_cipher-0.2.dist-info/METADATA
xts_cipher-0.2.dist-info/WHEEL
xts_cipher-0.2.dist-info/top_level.txt
xts_cipher-0.2.dist-info/RECORD
