Metadata-Version: 2.1
Name: xts_cipher
Version: 0.2
Summary: A Python package for encryption and decryption using the XOR-Transposition-Substitution (XTS) cipher algorithm.
Home-page: https://github.com/KrunalDalvi/xts_cipher
Author: Krunal Chandrakant Dalvi
Author-email: dalvikrunal15@gmail.com
Classifier: Programming Language :: Python :: 3
Classifier: License :: OSI Approved :: MIT License
Classifier: Operating System :: OS Independent
Requires-Python: >=3.6
License-File: LICENSE
Requires-Dist: numpy
